[{"Name":"Bouffalant","Elements":["normal"],"EV":2,"Stats":{"HP":0,"Attack":113,"Defense":96,"Speed":55,"Sp_Attack":40,"Sp_Defense":96},"Profile":{"Height":1.6,"Weight":94.6,"CatchRate":0,"GenderRatio":{"MaleRatio":50,"FemaleRatio":50},"EggGroup":"Field","HatchSteps":5100,"Abilities":"Soundproof, Reckless, Sap-sipper"},"DamegeWhenAttacked":[{"Element":"fighting","Coefficient":2},{"Element":"ghost","Coefficient":0}]},{"Name":"Hitmonchan","Elements":["fighting"],"EV":1,"Stats":{"HP":41,"Attack":106,"Defense":79,"Speed":76,"Sp_Attack":35,"Sp_Defense":111},"Profile":{"Height":1.4,"Weight":50.2,"CatchRate":0,"GenderRatio":{"MaleRatio":100,"FemaleRatio":0},"EggGroup":"Human-Like","HatchSteps":6375,"Abilities":"Inner-focus, Keen-eye, Iron-fist"},"DamegeWhenAttacked":[{"Element":"flying","Coefficient":2},{"Element":"rock","Coefficient":0.5},{"Element":"psychic","Coefficient":2},{"Element":"bug","Coefficient":0.5},{"Element":"fairy","Coefficient":2},{"Element":"grass","Coefficient":0.5},{"Element":"","Coefficient":0},{"Element":"dark","Coefficient":0.5}]},{"Name":"Rotom","Elements":["electric","ghost"],"EV":0,"Stats":{"HP":45,"Attack":50,"Defense":77,"Speed":91,"Sp_Attack":95,"Sp_Defense":77},"Profile":{"Height":0.3,"Weight":0.3,"CatchRate":0,"GenderRatio":{"MaleRatio":0,"FemaleRatio":0},"EggGroup":"Amorphous","HatchSteps":5100,"Abilities":"Levitate"},"DamegeWhenAttacked":[{"Element":"ghost","Coefficient":2},{"Element":"poison","Coefficient":0.5},{"Element":"dark","Coefficient":2},{"Element":"bug","Coefficient":0.5},{"Element":"ground","Coefficient":2},{"Element":"flying","Coefficient":0.5},{"Element":"","Coefficient":0},{"Element":"steel","Coefficient":0.5},{"Element":"","Coefficient":0},{"Element":"electric","Coefficient":0.5},{"Element":"","Coefficient":0},{"Element":"normal","Coefficient":0},{"Element":"","Coefficient":0},{"Element":"fighting","Coefficient":0}]}]
